discord_poster/__init__.py
discord_poster/DiscordPoster.py
discord_poster-0.1.0.dist-info/LICENSE
discord_poster-0.1.0.dist-info/METADATA
discord_poster-0.1.0.dist-info/WHEEL
discord_poster-0.1.0.dist-info/RECORD
